[
  { "Skibidi": [{ "channel": "youtube", "time": "10:34AM on Jul 10, 2023" }] },
  {
    "Song by Little Big": [
      { "channel": "youtube", "time": "10:34AM on Jul 10, 2023" }
    ]
  },
  { "Toilet": [{ "channel": "youtube", "time": "10:34AM on Jul 10, 2023" }] },
  { "Topic": [{ "channel": "youtube", "time": "10:34AM on Jul 10, 2023" }] },
  { "June": [{ "channel": "youtube", "time": "10:34AM on Jul 10, 2023" }] },
  { "Month": [{ "channel": "youtube", "time": "10:34AM on Jul 10, 2023" }] },
  { "Hot pot": [{ "channel": "youtube", "time": "10:34AM on Jul 10, 2023" }] },
  { "Dish": [{ "channel": "youtube", "time": "10:34AM on Jul 10, 2023" }] },
  {
    "Play Together": [
      { "channel": "youtube", "time": "10:34AM on Jul 10, 2023" }
    ]
  },
  {
    "Online game": [{ "channel": "youtube", "time": "10:34AM on Jul 10, 2023" }]
  },
  { "đammê": [{ "channel": "tiktok", "time": "10:34AM on Jul 10, 2023" }] },
  {
    "khoiluanhangiancuatoi": [
      { "channel": "tiktok", "time": "10:34AM on Jul 10, 2023" }
    ]
  },
  {
    "gaixinhtrungquoc": [
      { "channel": "tiktok", "time": "10:34AM on Jul 10, 2023" }
    ]
  },
  {
    "gaixinhtrungquoc": [
      { "channel": "tiktok", "time": "10:34AM on Jul 10, 2023" }
    ]
  },
  {
    "duongduong": [{ "channel": "tiktok", "time": "10:34AM on Jul 10, 2023" }]
  },
  { "dlow": [{ "channel": "tiktok", "time": "10:34AM on Jul 10, 2023" }] },
  {
    "Concacaf Gold Cup": [
      { "channel": "google", "time": "10:34AM on Jul 10, 2023" }
    ]
  },
  {
    "Canada men's national soccer team": [
      { "channel": "google", "time": "10:34AM on Jul 10, 2023" }
    ]
  },
  {
    "Guatemala national football team": [
      { "channel": "google", "time": "10:34AM on Jul 10, 2023" }
    ]
  },
  {
    "Jamaica national football team": [
      { "channel": "google", "time": "10:34AM on Jul 10, 2023" }
    ]
  },
  {
    "United States men's national soccer team": [
      { "channel": "google", "time": "10:34AM on Jul 10, 2023" }
    ]
  },
  { "Concacaf": [{ "channel": "google", "time": "10:34AM on Jul 10, 2023" }] },
  {
    "NBA Summer League": [
      { "channel": "google", "time": "10:34AM on Jul 10, 2023" }
    ]
  },
  { "NBA": [{ "channel": "google", "time": "10:34AM on Jul 10, 2023" }] },
  {
    "San Antonio Spurs": [
      { "channel": "google", "time": "10:34AM on Jul 10, 2023" }
    ]
  },
  {
    "Portland Trail Blazers": [
      { "channel": "google", "time": "10:34AM on Jul 10, 2023" }
    ]
  },
  {
    "Salt Lake City": [
      { "channel": "google", "time": "10:34AM on Jul 10, 2023" }
    ]
  },
  { "Nghe An": [{ "channel": "google", "time": "10:34AM on Jul 10, 2023" }] },
  {
    "People's Council": [
      { "channel": "google", "time": "10:34AM on Jul 10, 2023" }
    ]
  },
  { "Cadre": [{ "channel": "google", "time": "10:34AM on Jul 10, 2023" }] },
  {
    "New Zealand women's national football team": [
      { "channel": "google", "time": "10:34AM on Jul 10, 2023" }
    ]
  },
  {
    "Vietnam women's national football team": [
      { "channel": "google", "time": "10:34AM on Jul 10, 2023" }
    ]
  },
  {
    "Mai Duc Chung": [
      { "channel": "google", "time": "10:34AM on Jul 10, 2023" }
    ]
  },
  {
    "FIFA World Cup hosts": [
      { "channel": "google", "time": "10:34AM on Jul 10, 2023" }
    ]
  },
  { "FIFA": [{ "channel": "google", "time": "10:34AM on Jul 10, 2023" }] },
  {
    "International Friendlies": [
      { "channel": "google", "time": "10:34AM on Jul 10, 2023" }
    ]
  },
  {
    "Hoan Kiem turtle": [
      { "channel": "google", "time": "10:34AM on Jul 10, 2023" }
    ]
  },
  {
    "Hoàn Kiếm Lake": [
      { "channel": "google", "time": "10:34AM on Jul 10, 2023" }
    ]
  },
  {
    "Juventus F.C.": [
      { "channel": "google", "time": "10:34AM on Jul 10, 2023" }
    ]
  },
  {
    "UEFA Champions League": [
      { "channel": "google", "time": "10:34AM on Jul 10, 2023" }
    ]
  },
  {
    "Government of Vietnam": [
      { "channel": "google", "time": "10:34AM on Jul 10, 2023" }
    ]
  },
  {
    "Standing Committee of the National Assembly": [
      { "channel": "google", "time": "10:34AM on Jul 10, 2023" }
    ]
  },
  {
    "Paulo Dybala": [{ "channel": "google", "time": "10:34AM on Jul 10, 2023" }]
  },
  {
    "Chelsea F.C.": [{ "channel": "google", "time": "10:34AM on Jul 10, 2023" }]
  },
  { "A.S. Roma": [{ "channel": "google", "time": "10:34AM on Jul 10, 2023" }] },
  {
    "Mauricio Pochettino": [
      { "channel": "google", "time": "10:34AM on Jul 10, 2023" }
    ]
  },
  {
    "José Mourinho": [
      { "channel": "google", "time": "10:34AM on Jul 10, 2023" }
    ]
  },
  {
    "Argentina national football team": [
      { "channel": "google", "time": "10:34AM on Jul 10, 2023" }
    ]
  },
  {
    "Thiago Silva": [{ "channel": "google", "time": "10:34AM on Jul 10, 2023" }]
  },
  {
    "UEFA Europa League": [
      { "channel": "google", "time": "10:34AM on Jul 10, 2023" }
    ]
  },
  { "Da Nang": [{ "channel": "google", "time": "10:34AM on Jul 10, 2023" }] },
  { "Business": [{ "channel": "google", "time": "10:34AM on Jul 10, 2023" }] },
  { "Vietnam": [{ "channel": "google", "time": "10:34AM on Jul 10, 2023" }] },
  {
    "Personal income": [
      { "channel": "google", "time": "10:34AM on Jul 10, 2023" }
    ]
  },
  {
    "Settlement": [{ "channel": "google", "time": "10:34AM on Jul 10, 2023" }]
  },
  { "Hanoi": [{ "channel": "google", "time": "10:34AM on Jul 10, 2023" }] },
  {
    "University of Transport and Communications": [
      { "channel": "google", "time": "10:34AM on Jul 10, 2023" }
    ]
  },
  { "Business": [{ "channel": "google", "time": "10:34AM on Jul 10, 2023" }] },
  { "Cong Ly": [{ "channel": "google", "time": "10:34AM on Jul 10, 2023" }] },
  {
    "People's Artist": [
      { "channel": "google", "time": "10:34AM on Jul 10, 2023" }
    ]
  },
  { "Vietnam": [{ "channel": "google", "time": "10:34AM on Jul 10, 2023" }] },
  {
    "Vietnam Basketball Association": [
      { "channel": "google", "time": "10:34AM on Jul 10, 2023" }
    ]
  },
  {
    "Hanoi Buffaloes": [
      { "channel": "google", "time": "10:34AM on Jul 10, 2023" }
    ]
  },
  {
    "Saigon Heat": [{ "channel": "google", "time": "10:34AM on Jul 10, 2023" }]
  },
  {
    "Thang Long Warriors": [
      { "channel": "google", "time": "10:34AM on Jul 10, 2023" }
    ]
  },
  {
    "North Korea": [{ "channel": "google", "time": "10:34AM on Jul 10, 2023" }]
  },
  { "Pyongyang": [{ "channel": "google", "time": "10:34AM on Jul 10, 2023" }] },
  {
    "South Korea": [{ "channel": "google", "time": "10:34AM on Jul 10, 2023" }]
  },
  {
    "Ho Chi Minh City": [
      { "channel": "google", "time": "10:34AM on Jul 10, 2023" }
    ]
  },
  {
    "North-South power line": [
      { "channel": "google", "time": "10:34AM on Jul 10, 2023" }
    ]
  },
  {
    "Vietnam Electricity": [
      { "channel": "google", "time": "10:34AM on Jul 10, 2023" }
    ]
  },
  {
    "Ministry of Industry and Trade": [
      { "channel": "google", "time": "10:34AM on Jul 10, 2023" }
    ]
  },
  { "Business": [{ "channel": "google", "time": "10:34AM on Jul 10, 2023" }] },
  { "Business": [{ "channel": "google", "time": "10:34AM on Jul 10, 2023" }] },
  {
    "Portugal national football team": [
      { "channel": "google", "time": "10:34AM on Jul 10, 2023" }
    ]
  },
  {
    "Vietnam women's national football team": [
      { "channel": "google", "time": "10:34AM on Jul 10, 2023" }
    ]
  },
  {
    "England women's national football team": [
      { "channel": "google", "time": "10:34AM on Jul 10, 2023" }
    ]
  },
  {
    "UEFA European Championship": [
      { "channel": "google", "time": "10:34AM on Jul 10, 2023" }
    ]
  },
  { "Vietnam": [{ "channel": "google", "time": "10:34AM on Jul 10, 2023" }] },
  {
    "Real Madrid CF": [
      { "channel": "google", "time": "10:34AM on Jul 10, 2023" }
    ]
  },
  { "Vietnam": [{ "channel": "google", "time": "10:34AM on Jul 10, 2023" }] },
  {
    "Rice vermicelli with fried tofu and shrimp paste": [
      { "channel": "google", "time": "10:34AM on Jul 10, 2023" }
    ]
  },
  {
    "Ho Chi Minh City": [
      { "channel": "google", "time": "10:34AM on Jul 10, 2023" }
    ]
  },
  { "Cao Bang": [{ "channel": "google", "time": "10:34AM on Jul 10, 2023" }] },
  { "Vietnam": [{ "channel": "google", "time": "10:34AM on Jul 10, 2023" }] },
  {
    "Đồn Biên Phòng Ngọc Côn": [
      { "channel": "google", "time": "10:34AM on Jul 10, 2023" }
    ]
  },
  {
    "President of the United States": [
      { "channel": "google", "time": "10:34AM on Jul 10, 2023" }
    ]
  },
  { "Joe Biden": [{ "channel": "google", "time": "10:34AM on Jul 10, 2023" }] },
  {
    "Tom Cruise": [{ "channel": "google", "time": "10:34AM on Jul 10, 2023" }]
  },
  {
    "Mission: Impossible": [
      { "channel": "google", "time": "10:34AM on Jul 10, 2023" }
    ]
  },
  {
    "Ethan Hunt": [{ "channel": "google", "time": "10:34AM on Jul 10, 2023" }]
  },
  {
    "Christopher McQuarrie": [
      { "channel": "google", "time": "10:34AM on Jul 10, 2023" }
    ]
  },
  { "Vn-Index": [{ "channel": "google", "time": "10:34AM on Jul 10, 2023" }] },
  {
    "Hoa Phat Group": [
      { "channel": "google", "time": "10:34AM on Jul 10, 2023" }
    ]
  },
  {
    "Ho Chi Minh City Stock Exchange": [
      { "channel": "google", "time": "10:34AM on Jul 10, 2023" }
    ]
  },
  { "Vietnam": [{ "channel": "google", "time": "10:34AM on Jul 10, 2023" }] },
  { "Business": [{ "channel": "google", "time": "10:34AM on Jul 10, 2023" }] },
  { "Quảng Nam": [{ "channel": "google", "time": "10:34AM on Jul 10, 2023" }] },
  { "Hội An": [{ "channel": "google", "time": "10:34AM on Jul 10, 2023" }] },
  {
    "Provinces of Vietnam": [
      { "channel": "google", "time": "10:34AM on Jul 10, 2023" }
    ]
  },
  { "Business": [{ "channel": "google", "time": "10:34AM on Jul 10, 2023" }] },
  {
    "People's Council": [
      { "channel": "google", "time": "10:34AM on Jul 10, 2023" }
    ]
  },
  {
    "member of the National Assembly of Vietnam": [
      { "channel": "google", "time": "10:34AM on Jul 10, 2023" }
    ]
  },
  {
    "Provinces of Vietnam": [
      { "channel": "google", "time": "10:34AM on Jul 10, 2023" }
    ]
  },
  {
    "Thanh Hoa Province": [
      { "channel": "google", "time": "10:34AM on Jul 10, 2023" }
    ]
  },
  { "Nghe An": [{ "channel": "google", "time": "10:34AM on Jul 10, 2023" }] },
  {
    "Provincial Party Committee": [
      { "channel": "google", "time": "10:34AM on Jul 10, 2023" }
    ]
  },
  {
    "Secretary of Provincial Party Committee": [
      { "channel": "google", "time": "10:34AM on Jul 10, 2023" }
    ]
  },
  { "": [{}] }
]
